LICENSE
MANIFEST.in
README.md
setup.py
passletters/__init__.py
passletters/passletters.py
passletters.egg-info/PKG-INFO
passletters.egg-info/SOURCES.txt
passletters.egg-info/dependency_links.txt
passletters.egg-info/entry_points.txt
passletters.egg-info/requires.txt
passletters.egg-info/top_level.txt